dbx_marker-1.0.6.dist-info/METADATA
dbx_marker-1.0.6.dist-info/WHEEL
dbx_marker-1.0.6.dist-info/entry_points.txt
dbx_marker-1.0.6.dist-info/licenses/LICENSE
dbx_marker/__init__.py
dbx_marker/config.py
dbx_marker/exceptions.py
dbx_marker/manager.py
dbx_marker/sqls.py
dbx_marker/utils.py
dbx_marker-1.0.6.dist-info/RECORD
