Metadata-Version: 2.1
Name: dbx-marker
Version: 1.0.6
Summary: Easily manage incremental progress using watermarks in your Databricks data pipelines
Author-Email: Jelther Goncalves <hello@jelther.dev>
License: MIT License
Requires-Python: >=3.10
Requires-Dist: loguru>=0.7.3
